AUTHORS
LICENSE
MANIFEST.in
README.md
setup.py
unties/__init__.py
unties/class_helps.py
unties/counter.py
unties/unit_helpers.py
unties/units.py
unties/units_group.py
unties.egg-info/PKG-INFO
unties.egg-info/SOURCES.txt
unties.egg-info/dependency_links.txt
unties.egg-info/not-zip-safe
unties.egg-info/top_level.txt
unties/properties/__init__.py
unties/properties/air.py
unties/properties/benzene.py
unties/properties/f_values.py
unties/properties/transcendentals.py
unties/properties/water.py
unties/utilities/__init__.py
unties/utilities/errors.py
unties/utilities/utilities.py