Metadata-Version: 1.0
Name: unties
Version: 0.3.0
Summary: The unit handler
Home-page: https://github.com/spejamchr/unties
Author: Spencer Christiansen
Author-email: jc.spencer92@gmail.com
License: MIT
Platform: UNKNOWN
